EasyImports/__init__.py
EasyImports/easyimports.py
EasyImports-0.0.3.dist-info/LICENSE
EasyImports-0.0.3.dist-info/METADATA
EasyImports-0.0.3.dist-info/WHEEL
EasyImports-0.0.3.dist-info/top_level.txt
EasyImports-0.0.3.dist-info/RECORD
