Metadata-Version: 2.1
Name: EasyImports
Version: 0.0.3
Summary: A python package to import files from an adjacent folder
Home-page: https://github.com/Skagames/EasyImports
Author: Skagames
Author-email: support@skahosting.xyz
License: UNKNOWN
Project-URL: Bug Tracker, https://github.com/Skagames/EasyImports/issues
Platform: UNKNOWN
Classifier: Programming Language :: Python :: 3
Classifier: License :: OSI Approved :: MIT License
Classifier: Operating System :: OS Independent
Requires-Python: >=3.6
License-File: LICENSE
